seeker/__init__.py
seeker/command_line.py
seeker/seeker.py
seeker/models/MatModel0.h5
seeker/models/MatModelPRO.h5
seeker/models/model.h5
seeker/tests/__init__.py
seeker/tests/test_seeker.py
seeker-1.0.3.dist-info/LICENSE
seeker-1.0.3.dist-info/METADATA
seeker-1.0.3.dist-info/WHEEL
seeker-1.0.3.dist-info/entry_points.txt
seeker-1.0.3.dist-info/top_level.txt
seeker-1.0.3.dist-info/RECORD
