Metadata-Version: 2.1
Name: seeker
Version: 1.0.3
Summary: Predict bacterial or phage sequence
Home-page: http://seeker.pythonanywhere.com
Author: Ayal B. Gussow, Noam Auslander
Author-email: ayal.gussow@gmail.com, noamaus@gmail.com
License: UNKNOWN
Platform: UNKNOWN
Classifier: Programming Language :: Python :: 3
Classifier: License :: OSI Approved :: GNU General Public License (GPL)
Classifier: Operating System :: OS Independent
Requires-Python: >=3.6
Requires-Dist: numpy (>=1.17.3)
Requires-Dist: tensorflow (>=2.0.0)
